imperfect/__init__.py
imperfect/__version__.py
imperfect/_version.py
imperfect/py.typed
imperfect/types.py
imperfect/verify.py
imperfect/tests/__init__.py
imperfect/tests/__main__.py
imperfect/tests/editing.py
imperfect/tests/imperfect.py
imperfect/tests/imperfect_hypothesis.py
imperfect-0.4.0.dist-info/licenses/LICENSE
imperfect-0.4.0.dist-info/METADATA
imperfect-0.4.0.dist-info/WHEEL
imperfect-0.4.0.dist-info/top_level.txt
imperfect-0.4.0.dist-info/RECORD
