Metadata-Version: 2.4
Name: imperfect
Version: 0.4.0
Summary: A CST-based config editor for configparser
Home-page: https://github.com/advice-animal/imperfect/
Author: Tim Hatch
Author-email: tim@timhatch.com
License: MIT
Requires-Python: >=3.8
License-File: LICENSE
Requires-Dist: moreorless>=0.2.0
Provides-Extra: dev
Requires-Dist: ruff==0.8.0; extra == "dev"
Requires-Dist: checkdeps==0.9.0; extra == "dev"
Requires-Dist: mypy==1.13.0; extra == "dev"
Requires-Dist: tox==4.23.2; extra == "dev"
Provides-Extra: test
Requires-Dist: coverage>=6; extra == "test"
Requires-Dist: parameterized>=0.6.1; extra == "test"
Requires-Dist: hypothesis==6.96.1; extra == "test"
Dynamic: license-file
